{"primaryContentSections":[{"content":[{"type":"heading","level":2,"text":"Overview","anchor":"Overview"},{"type":"paragraph","inlineContent":[{"type":"text","text":"Staq server APIs provides some listed data in paginated type. TrustlessSDK provide a way to handle paginated API request via "},{"isActive":true,"type":"reference","identifier":"doc:\/\/com.staq.TrustlessSDK\/documentation\/TrustlessSDK\/Paginator"},{"type":"text","text":" object. It manages the retrieval of data in pages, tracking the current page number, total items, and handling the request status."}]},{"level":2,"text":"Gettin Started","anchor":"Gettin-Started","type":"heading"},{"inlineContent":[{"type":"text","text":"Paginator provides:"}],"type":"paragraph"},{"type":"unorderedList","items":[{"content":[{"inlineContent":[{"type":"reference","isActive":true,"identifier":"doc:\/\/com.staq.TrustlessSDK\/documentation\/TrustlessSDK\/Paginator\/fetchFirstPage(completion:)"},{"text":", you can use it to fetch first page or to reset previous results;","type":"text"}],"type":"paragraph"}]},{"content":[{"type":"paragraph","inlineContent":[{"identifier":"doc:\/\/com.staq.TrustlessSDK\/documentation\/TrustlessSDK\/Paginator\/fetchNextPage(completion:)","isActive":true,"type":"reference"},{"text":", you can use this method to fetch next pages,","type":"text"}]}]}]},{"type":"paragraph","inlineContent":[{"text":"to perform retrieval of data in pages.","type":"text"}]},{"content":[{"type":"paragraph","inlineContent":[{"type":"text","text":""},{"code":"fetchNextPage(completion:)","type":"codeVoice"},{"type":"text","text":" should be called after "},{"code":"fetchFirstPage(completion:)","type":"codeVoice"},{"type":"text","text":"."}]}],"name":"Note","style":"note","type":"aside"},{"type":"paragraph","inlineContent":[{"text":"To retrive results Paginator provides ","type":"text"},{"isActive":true,"type":"reference","identifier":"doc:\/\/com.staq.TrustlessSDK\/documentation\/TrustlessSDK\/Paginator\/results"},{"type":"text","text":", this property includes all results."}]},{"type":"paragraph","inlineContent":[{"text":"To handle result you can assign handlers to paginator:","type":"text"}]},{"type":"unorderedList","items":[{"content":[{"type":"paragraph","inlineContent":[{"identifier":"doc:\/\/com.staq.TrustlessSDK\/documentation\/TrustlessSDK\/Paginator\/setResultsHandler(_:)","type":"reference","isActive":true},{"text":", to handle results;","type":"text"}]}]},{"content":[{"inlineContent":[{"type":"reference","identifier":"doc:\/\/com.staq.TrustlessSDK\/documentation\/TrustlessSDK\/Paginator\/setFailureHandler(_:)","isActive":true},{"type":"text","text":", to handle errors."}],"type":"paragraph"}]}]},{"inlineContent":[{"text":"Also Paginator provides additional properties:","type":"text"}],"type":"paragraph"},{"type":"unorderedList","items":[{"content":[{"type":"paragraph","inlineContent":[{"identifier":"doc:\/\/com.staq.TrustlessSDK\/documentation\/TrustlessSDK\/Paginator\/pageNumber","isActive":true,"type":"reference"},{"type":"text","text":", stores the current page number;"}]}]},{"content":[{"inlineContent":[{"type":"reference","isActive":true,"identifier":"doc:\/\/com.staq.TrustlessSDK\/documentation\/TrustlessSDK\/Paginator\/total"},{"type":"text","text":", stores the total number of items;"}],"type":"paragraph"}]},{"content":[{"type":"paragraph","inlineContent":[{"type":"reference","identifier":"doc:\/\/com.staq.TrustlessSDK\/documentation\/TrustlessSDK\/Paginator\/requestStatus","isActive":true},{"text":", stores the current status of the data request (","type":"text"},{"identifier":"doc:\/\/com.staq.TrustlessSDK\/documentation\/TrustlessSDK\/RequestStatus","isActive":true,"type":"reference"},{"text":");","type":"text"}]}]},{"content":[{"type":"paragraph","inlineContent":[{"isActive":true,"identifier":"doc:\/\/com.staq.TrustlessSDK\/documentation\/TrustlessSDK\/Paginator\/reachedLastPage","type":"reference"},{"text":", indicates whether the last page has been reached;","type":"text"}]}]}]},{"inlineContent":[{"type":"text","text":"To cancel outgoing request Paginator provides optional "},{"isActive":true,"identifier":"doc:\/\/com.staq.TrustlessSDK\/documentation\/TrustlessSDK\/Paginator\/currentCancelRequestCallback","type":"reference"},{"text":", that is asseable after first call of retrieval data methods.","type":"text"}],"type":"paragraph"},{"level":2,"type":"heading","anchor":"Basic-Example","text":"Basic Example"},{"syntax":"swift","type":"codeListing","code":["import UIKit","import TrustlessSDK","","class ViewController: UIViewController, UITableViewDataSource, UITableViewDelegate, UIScrollViewDelegate {","    let paginator = TrustlessSDK.cardsProvider.getCardsPaginator(pageSize: 10)","","    override func viewDidLoad() {","        super.viewDidLoad()","        _ = paginator.fetchFirstPage { _ in","            self.tableView.reloadData()","        }","    }","","    func insertElements(newItemsCount: Int) {","        let startIndex = paginator.results.count - newItemsCount","        let indexPaths = (startIndex ..< paginator.results.count).map { IndexPath(row: $0, section: 0) }","","        tableView.beginUpdates()","        tableView.insertRows(at: indexPaths, with: .automatic)","        tableView.endUpdates()","    }","","    \/\/ TableViewDelegate","","    override func tableView(_ tableView: UITableView, numberOfRowsInSection section: Int) -> Int {","        return paginator.results.count","    }","","    override func tableView(_ tableView: UITableView, cellForRowAt indexPath: IndexPath) -> UITableViewCell {","        return UITableViewCell()","    }","","    override func tableView(_ tableView: UITableView, didSelectRowAt indexPath: IndexPath) {}","","    \/\/ ScrollViewDelegate","","    override func scrollViewDidScroll(_ scrollView: UIScrollView) {","        guard !paginator.reachedLastPage else { return }","","        let offsetY = scrollView.contentOffset.y","        let contentHeight = scrollView.contentSize.height","        let height = scrollView.frame.size.height","","        if offsetY > contentHeight - height * 1, !(paginator.requestStatus == .inProgress) {","            cancelCallback = paginator.fetchNextPage { result in","                self.endLoadingMoreItems()","                switch result {","                case .success(let data):","                    self.insertElements(newItemsCount: data.count)","                case .failure:","                    break","                }","            }","        }","    }","}"]}],"kind":"content"}],"identifier":{"interfaceLanguage":"swift","url":"doc:\/\/com.staq.TrustlessSDK\/documentation\/TrustlessSDK\/PaginatorArticle"},"seeAlsoSections":[{"title":"Articles","generated":true,"identifiers":["doc:\/\/com.staq.TrustlessSDK\/documentation\/TrustlessSDK\/IntegrationArticle","doc:\/\/com.staq.TrustlessSDK\/documentation\/TrustlessSDK\/RequestSendingArticle","doc:\/\/com.staq.TrustlessSDK\/documentation\/TrustlessSDK\/KYCStepsManagerArticle"]}],"hierarchy":{"paths":[["doc:\/\/com.staq.TrustlessSDK\/documentation\/TrustlessSDK"]]},"metadata":{"modules":[{"name":"TrustlessSDK"}],"title":"Paginator Usage","role":"article","roleHeading":"Article"},"variants":[{"paths":["\/documentation\/trustlesssdk\/paginatorarticle"],"traits":[{"interfaceLanguage":"swift"}]}],"schemaVersion":{"patch":0,"major":0,"minor":3},"kind":"article","sections":[],"abstract":[{"type":"text","text":"Sending and handling paginated requests: Paginator helper."}],"references":{"doc://com.staq.TrustlessSDK/documentation/TrustlessSDK":{"abstract":[],"kind":"symbol","role":"collection","url":"\/documentation\/trustlesssdk","identifier":"doc:\/\/com.staq.TrustlessSDK\/documentation\/TrustlessSDK","type":"topic","title":"TrustlessSDK"},"doc://com.staq.TrustlessSDK/documentation/TrustlessSDK/Paginator/currentCancelRequestCallback":{"title":"currentCancelRequestCallback","fragments":[{"kind":"keyword","text":"var"},{"text":" ","kind":"text"},{"kind":"identifier","text":"currentCancelRequestCallback"},{"text":": ","kind":"text"},{"text":"CancelCallback","preciseIdentifier":"s:12TrustlessSDK14CancelCallbacka","kind":"typeIdentifier"},{"kind":"text","text":"?"}],"type":"topic","role":"symbol","abstract":[{"text":"Callback for the current cancel request action.","type":"text"}],"kind":"symbol","identifier":"doc:\/\/com.staq.TrustlessSDK\/documentation\/TrustlessSDK\/Paginator\/currentCancelRequestCallback","url":"\/documentation\/trustlesssdk\/paginator\/currentcancelrequestcallback"},"doc://com.staq.TrustlessSDK/documentation/TrustlessSDK/Paginator/total":{"url":"\/documentation\/trustlesssdk\/paginator\/total","kind":"symbol","title":"total","identifier":"doc:\/\/com.staq.TrustlessSDK\/documentation\/TrustlessSDK\/Paginator\/total","role":"symbol","type":"topic","fragments":[{"kind":"keyword","text":"var"},{"text":" ","kind":"text"},{"text":"total","kind":"identifier"},{"kind":"text","text":": "},{"text":"Int","preciseIdentifier":"s:Si","kind":"typeIdentifier"}],"abstract":[{"type":"text","text":"The total number of items available, as reported by the server."}]},"doc://com.staq.TrustlessSDK/documentation/TrustlessSDK/Paginator/results":{"title":"results","fragments":[{"text":"var","kind":"keyword"},{"kind":"text","text":" "},{"kind":"identifier","text":"results"},{"text":": [","kind":"text"},{"preciseIdentifier":"s:12TrustlessSDK9PaginatorC7Elementxmfp","kind":"typeIdentifier","text":"Element"},{"kind":"text","text":"]"}],"type":"topic","role":"symbol","abstract":[{"text":"An array of items of type ","type":"text"},{"code":"Element","type":"codeVoice"},{"text":" that have been fetched.","type":"text"}],"kind":"symbol","url":"\/documentation\/trustlesssdk\/paginator\/results","identifier":"doc:\/\/com.staq.TrustlessSDK\/documentation\/TrustlessSDK\/Paginator\/results"},"doc://com.staq.TrustlessSDK/documentation/TrustlessSDK/RequestSendingArticle":{"url":"\/documentation\/trustlesssdk\/requestsendingarticle","title":"Request Sending","type":"topic","kind":"article","abstract":[{"type":"text","text":"Sending requests to and receiving responses from Staq Server APIs: A detailed walkthrough."}],"identifier":"doc:\/\/com.staq.TrustlessSDK\/documentation\/TrustlessSDK\/RequestSendingArticle","role":"article"},"doc://com.staq.TrustlessSDK/documentation/TrustlessSDK/Paginator/setFailureHandler(_:)":{"fragments":[{"text":"func","kind":"keyword"},{"text":" ","kind":"text"},{"text":"setFailureHandler","kind":"identifier"},{"text":"(","kind":"text"},{"text":"PaginatorFailureHandler","preciseIdentifier":"s:12TrustlessSDK23PaginatorFailureHandlera","kind":"typeIdentifier"},{"text":"<","kind":"text"},{"text":"Element","kind":"typeIdentifier","preciseIdentifier":"s:12TrustlessSDK9PaginatorC7Elementxmfp"},{"kind":"text","text":">)"}],"kind":"symbol","abstract":[{"type":"text","text":"Sets a handler to be called when a fetch operation fails."}],"url":"\/documentation\/trustlesssdk\/paginator\/setfailurehandler(_:)","identifier":"doc:\/\/com.staq.TrustlessSDK\/documentation\/TrustlessSDK\/Paginator\/setFailureHandler(_:)","role":"symbol","title":"setFailureHandler(_:)","type":"topic"},"doc://com.staq.TrustlessSDK/documentation/TrustlessSDK/Paginator/pageNumber":{"url":"\/documentation\/trustlesssdk\/paginator\/pagenumber","kind":"symbol","type":"topic","identifier":"doc:\/\/com.staq.TrustlessSDK\/documentation\/TrustlessSDK\/Paginator\/pageNumber","title":"pageNumber","role":"symbol","abstract":[{"text":"The current page number being fetched or displayed.","type":"text"}],"fragments":[{"text":"var","kind":"keyword"},{"kind":"text","text":" "},{"kind":"identifier","text":"pageNumber"},{"kind":"text","text":": "},{"kind":"typeIdentifier","preciseIdentifier":"s:Si","text":"Int"}]},"doc://com.staq.TrustlessSDK/documentation/TrustlessSDK/IntegrationArticle":{"kind":"article","title":"Integration","identifier":"doc:\/\/com.staq.TrustlessSDK\/documentation\/TrustlessSDK\/IntegrationArticle","type":"topic","url":"\/documentation\/trustlesssdk\/integrationarticle","abstract":[{"text":"Integration of TrustlessSDK: Client Secrets and Client Certificate.","type":"text"}],"role":"article"},"doc://com.staq.TrustlessSDK/documentation/TrustlessSDK/Paginator/fetchFirstPage(completion:)":{"title":"fetchFirstPage(completion:)","fragments":[{"kind":"keyword","text":"func"},{"text":" ","kind":"text"},{"text":"fetchFirstPage","kind":"identifier"},{"kind":"text","text":"("},{"text":"completion","kind":"externalParam"},{"kind":"text","text":": "},{"kind":"typeIdentifier","preciseIdentifier":"s:12TrustlessSDK14ResultCallbacka","text":"ResultCallback"},{"text":"<[","kind":"text"},{"text":"Element","kind":"typeIdentifier","preciseIdentifier":"s:12TrustlessSDK9PaginatorC7Elementxmfp"},{"kind":"text","text":"]>) -> "},{"preciseIdentifier":"s:12TrustlessSDK14CancelCallbacka","kind":"typeIdentifier","text":"CancelCallback"},{"text":"?","kind":"text"}],"type":"topic","role":"symbol","abstract":[{"text":"Fetches the first page of data, resetting any previous results.","type":"text"}],"kind":"symbol","url":"\/documentation\/trustlesssdk\/paginator\/fetchfirstpage(completion:)","identifier":"doc:\/\/com.staq.TrustlessSDK\/documentation\/TrustlessSDK\/Paginator\/fetchFirstPage(completion:)"},"doc://com.staq.TrustlessSDK/documentation/TrustlessSDK/RequestStatus":{"fragments":[{"text":"enum","kind":"keyword"},{"kind":"text","text":" "},{"text":"RequestStatus","kind":"identifier"}],"identifier":"doc:\/\/com.staq.TrustlessSDK\/documentation\/TrustlessSDK\/RequestStatus","role":"symbol","title":"RequestStatus","kind":"symbol","abstract":[{"type":"text","text":"Represents the current status of a paginated data request."}],"type":"topic","navigatorTitle":[{"text":"RequestStatus","kind":"identifier"}],"url":"\/documentation\/trustlesssdk\/requeststatus"},"doc://com.staq.TrustlessSDK/documentation/TrustlessSDK/Paginator/fetchNextPage(completion:)":{"url":"\/documentation\/trustlesssdk\/paginator\/fetchnextpage(completion:)","title":"fetchNextPage(completion:)","type":"topic","kind":"symbol","abstract":[{"type":"text","text":"Fetches the next page of data based on the current page number."}],"identifier":"doc:\/\/com.staq.TrustlessSDK\/documentation\/TrustlessSDK\/Paginator\/fetchNextPage(completion:)","role":"symbol","fragments":[{"text":"func","kind":"keyword"},{"kind":"text","text":" "},{"text":"fetchNextPage","kind":"identifier"},{"kind":"text","text":"("},{"text":"completion","kind":"externalParam"},{"text":": ","kind":"text"},{"preciseIdentifier":"s:12TrustlessSDK14ResultCallbacka","kind":"typeIdentifier","text":"ResultCallback"},{"kind":"text","text":"<["},{"text":"Element","preciseIdentifier":"s:12TrustlessSDK9PaginatorC7Elementxmfp","kind":"typeIdentifier"},{"text":"]>) -> ","kind":"text"},{"text":"CancelCallback","preciseIdentifier":"s:12TrustlessSDK14CancelCallbacka","kind":"typeIdentifier"},{"kind":"text","text":"?"}]},"doc://com.staq.TrustlessSDK/documentation/TrustlessSDK/Paginator/setResultsHandler(_:)":{"title":"setResultsHandler(_:)","abstract":[{"text":"Sets a handler to be called with the results of each successful fetch operation.","type":"text"}],"url":"\/documentation\/trustlesssdk\/paginator\/setresultshandler(_:)","type":"topic","kind":"symbol","role":"symbol","fragments":[{"text":"func","kind":"keyword"},{"kind":"text","text":" "},{"text":"setResultsHandler","kind":"identifier"},{"text":"(","kind":"text"},{"text":"PaginatorResultsHandler","kind":"typeIdentifier","preciseIdentifier":"s:12TrustlessSDK23PaginatorResultsHandlera"},{"kind":"text","text":"<"},{"kind":"typeIdentifier","preciseIdentifier":"s:12TrustlessSDK9PaginatorC7Elementxmfp","text":"Element"},{"text":">)","kind":"text"}],"identifier":"doc:\/\/com.staq.TrustlessSDK\/documentation\/TrustlessSDK\/Paginator\/setResultsHandler(_:)"},"doc://com.staq.TrustlessSDK/documentation/TrustlessSDK/Paginator/reachedLastPage":{"type":"topic","url":"\/documentation\/trustlesssdk\/paginator\/reachedlastpage","title":"reachedLastPage","kind":"symbol","abstract":[{"type":"text","text":"Indicates whether the last page has been reached."}],"role":"symbol","identifier":"doc:\/\/com.staq.TrustlessSDK\/documentation\/TrustlessSDK\/Paginator\/reachedLastPage","fragments":[{"text":"var","kind":"keyword"},{"kind":"text","text":" "},{"kind":"identifier","text":"reachedLastPage"},{"text":": ","kind":"text"},{"text":"Bool","kind":"typeIdentifier","preciseIdentifier":"s:Sb"}]},"doc://com.staq.TrustlessSDK/documentation/TrustlessSDK/Paginator":{"abstract":[{"type":"text","text":"Manages paginated data fetching in a flexible and efficient manner."}],"identifier":"doc:\/\/com.staq.TrustlessSDK\/documentation\/TrustlessSDK\/Paginator","title":"Paginator","type":"topic","url":"\/documentation\/trustlesssdk\/paginator","role":"symbol","kind":"symbol","navigatorTitle":[{"kind":"identifier","text":"Paginator"}],"fragments":[{"text":"class","kind":"keyword"},{"text":" ","kind":"text"},{"text":"Paginator","kind":"identifier"}]},"doc://com.staq.TrustlessSDK/documentation/TrustlessSDK/KYCStepsManagerArticle":{"identifier":"doc:\/\/com.staq.TrustlessSDK\/documentation\/TrustlessSDK\/KYCStepsManagerArticle","abstract":[{"type":"text","text":"A class responsible for managing an individual step in the KYC process."}],"title":"KYC Steps Manager","url":"\/documentation\/trustlesssdk\/kycstepsmanagerarticle","kind":"article","role":"article","type":"topic"},"doc://com.staq.TrustlessSDK/documentation/TrustlessSDK/Paginator/requestStatus":{"fragments":[{"text":"var","kind":"keyword"},{"text":" ","kind":"text"},{"kind":"identifier","text":"requestStatus"},{"text":": ","kind":"text"},{"text":"RequestStatus","kind":"typeIdentifier","preciseIdentifier":"s:12TrustlessSDK13RequestStatusO"}],"identifier":"doc:\/\/com.staq.TrustlessSDK\/documentation\/TrustlessSDK\/Paginator\/requestStatus","title":"requestStatus","type":"topic","role":"symbol","abstract":[{"type":"text","text":"The current status of the data request (none, inProgress, done, failed)."}],"kind":"symbol","url":"\/documentation\/trustlesssdk\/paginator\/requeststatus"}}}